knapsack/.git
knapsack/.gitignore
knapsack/__init__.py
knapsack/account.py
knapsack/api.py
knapsack/blueprints.py
knapsack/kd_builder.py
knapsack/knapsack.py
knapsack/knapsack_dataset.py
knapsack/requirements.txt
knapsack/split.py
knapsack/storage/b2_storage_api.py
knapsack/storage/b2_store.py
knapsack/storage/base_store.py
knapsack/storage/fs_store.py
knapsack/storage_provider.py
knap-0.0.5.dist-info/LICENSE
knap-0.0.5.dist-info/METADATA
knap-0.0.5.dist-info/WHEEL
knap-0.0.5.dist-info/entry_points.txt
knap-0.0.5.dist-info/RECORD
